{
  "AWSTemplateFormatVersion": "2010-09-09",
  "Parameters": {
    "KeyName": {
      "Description": "Name of an existing EC2 KeyPair to enable SSH access to the instances",
      "Type": "String",
      "MinLength": "1",
      "MaxLength": "64",
      "AllowedPattern": "[-_ a-zA-Z0-9]*",
      "ConstraintDescription": "can contain only alphanumeric characters, spaces, dashes and underscores."
    },
    "InstanceType": {
      "Description": "EC2 instance type",
      "Type": "String",
      "Default": "m1.small",
      "AllowedValues": [
        "t1.micro",
        "m1.small",
        "m1.medium",
        "m1.large",
        "m1.xlarge",
        "c1.medium",
        "c1.xlarge",
        "hi1.4xlarge",
        "hs1.8xlarge",
        "m3.medium",
        "m3.large",
        "m3.xlarge",
        "m3.2xlarge",
        "c3.large",
        "c3.xlarge",
        "c3.2xlarge",
        "c3.4xlarge",
        "c3.8xlarge"
      ],
      "ConstraintDescription": "must be a valid EC2 instance type."
    }
  },
  "Mappings": {
    "MPAmimotov4": {
      "us-east-1": {
        "AMI": "ami-6228990a",
        "Location": "Virginia"
      },
      "us-west-2": {
        "AMI": "ami-e3b3f1d3",
        "Location": "Oregon"
      },
      "us-west-1": {
        "AMI": "ami-c5212a80",
        "Location": "N.California"
      },
      "eu-west-1": {
        "AMI": "ami-3402a243",
        "Location": "EU_Ireland"
      },
      "ap-southeast-1": {
        "AMI": "ami-f2d6f1a0",
        "Location": "Singapore"
      },
      "ap-southeast-2": {
        "AMI": "ami-ad7c1e97",
        "Location": "Sydney"
      },
      "ap-northeast-1": {
        "AMI": "ami-cfbd96ce",
        "Location": "Tokyo"
      },
      "sa-east-1": {
        "AMI": "ami-23ba0f3e",
        "Location": "Sao_Paul"
      }
    }
  },
  "Resources": {
    "LoadBalancer": {
      "Type": "AWS::ElasticLoadBalancing::LoadBalancer",
      "Properties": {
        "AvailabilityZones": [
          {
            "Fn::GetAtt": [
              "AmimotoSingle",
              "AvailabilityZone"
            ]
          }
        ],
        "HealthCheck": {
          "HealthyThreshold": "2",
          "Interval": "30",
          "Target": "TCP:80",
          "Timeout": "10",
          "UnhealthyThreshold": "2"
        },
        "Instances": [
          {
            "Ref": "AmimotoSingle"
          }
        ],
        "Listeners": [
          {
            "InstancePort": "80",
            "LoadBalancerPort": "80",
            "Protocol": "HTTP",
            "InstanceProtocol": "HTTP"
          },
          {
            "InstancePort": "443",
            "LoadBalancerPort": "443",
            "Protocol": "TCP",
            "InstanceProtocol": "TCP"
          }
        ]
      }
    },
    "AmimotoSingle": {
      "Type": "AWS::EC2::Instance",
      "Properties": {
        "DisableApiTermination": "FALSE",
        "ImageId": {
          "Fn::FindInMap": [
            "MPAmimotov4",
            {
              "Ref": "AWS::Region"
            },
            "AMI"
          ]
        },
        "InstanceType": {
          "Ref": "InstanceType"
        },
        "KeyName": {
          "Ref": "KeyName"
        },
        "SecurityGroupIds": [
          {
            "Ref": "sgAMIMOTO11AutogenByAWSMP"
          }
        ],
        "Monitoring": "false",
        "Tags": [
          {
            "Key": "Name",
            "Value": "mp-amimoto"
          }
        ]
      }
    },
    "sgAMIMOTO11AutogenByAWSMP": {
      "Type": "AWS::EC2::SecurityGroup",
      "Properties": {
        "GroupDescription": "This security group was generated by AWS Marketplace and is based on recommended settings for AMIMOTO version 11 provided by DigitalCube Co Ltd",
        "SecurityGroupIngress": [
          {
            "IpProtocol": "tcp",
            "FromPort": "22",
            "ToPort": "22",
            "CidrIp": "0.0.0.0/0"
          },
          {
            "IpProtocol": "tcp",
            "FromPort": "80",
            "ToPort": "80",
            "CidrIp": "0.0.0.0/0"
          }
        ]
      }
    }
  },
  "Description": "",
  "Outputs": {
    "WebSiteURL": {
      "Description": "WordPress Site URL (Please wait a few minutes for the upgrade of WordPress to access for the first time.)",
      "Value": {
        "Fn::Join": [
          "",
          [
            "http://",
            {
              "Fn::GetAtt": [
                "LoadBalancer",
                "DNSName"
              ]
            }
          ]
        ]
      }
    }
  }
}
